CHANGELOG.txt
LICENSE.txt
MANIFEST.in
README.txt
kranthoslib.py
setup.py
kranthoslib.egg-info/PKG-INFO
kranthoslib.egg-info/SOURCES.txt
kranthoslib.egg-info/dependency_links.txt
kranthoslib.egg-info/top_level.txt